malloy/__init__.py
malloy/__main__.py
malloy/runtime.py
malloy/data/__init__.py
malloy/data/connection.py
malloy/data/connection_manager.py
malloy/data/query_results.py
malloy/data/schema_cache.py
malloy/data/bigquery/__init__.py
malloy/data/bigquery/bq_connection.py
malloy/data/duckdb/__init__.py
malloy/data/duckdb/duckdb_connection.py
malloy/data/snowflake/__init__.py
malloy/data/snowflake/snowflake_connection.py
malloy/ipython/__init__.py
malloy/ipython/ipython_magic.py
malloy/ipython/tab_renderer.py
malloy/ipython/warnings.py
malloy/ipython/schema_view/__init__.py
malloy/ipython/schema_view/icons.py
malloy/ipython/schema_view/scripts.py
malloy/ipython/schema_view/styles.py
malloy/service/__init__.py
malloy/service/licenses-malloy-service.txt
malloy/service/malloy-service-linux-arm64
malloy/service/malloy-service-linux-x64
malloy/service/malloy-service-macos-x64
malloy/service/malloy-service-win-x64.exe
malloy/service/service_manager.py
malloy/services/__init__.py
malloy/services/v1/__init__.py
malloy/services/v1/compiler_pb2.py
malloy/services/v1/compiler_pb2.pyi
malloy/services/v1/compiler_pb2_grpc.py
malloy/utils/__init__.py
malloy/utils/third_party_licenses.py
malloy-2024.1096.dist-info/LICENSE
malloy-2024.1096.dist-info/METADATA
malloy-2024.1096.dist-info/WHEEL
malloy-2024.1096.dist-info/entry_points.txt
malloy-2024.1096.dist-info/top_level.txt
malloy-2024.1096.dist-info/RECORD
