Metadata-Version: 2.1
Name: malloy
Version: 2024.1096
Summary: Malloy is an experimental language for describing data relationships and transformations
License: Copyright 2023 Google LLC
Project-URL: Documentation, https://malloydata.dev
Project-URL: Source, https://github.com/malloydata/malloy-py
Project-URL: Issues, https://github.com/malloydata/malloy-py/issues
Project-URL: Changelog, https://github.com/malloydata/malloy-py/releases
Keywords: malloy
Classifier: Development Status :: 3 - Alpha
Classifier: License :: OSI Approved :: MIT License
Classifier: Programming Language :: Python :: 3
Requires-Python: >3.7
License-File: LICENSE
Requires-Dist: duckdb>=0.8.0
Requires-Dist: google-cloud-bigquery
Requires-Dist: snowflake-connector-python>=3.6.0
Requires-Dist: absl-py
Provides-Extra: dev
Requires-Dist: db-dtypes; extra == "dev"
Requires-Dist: grpcio-tools; extra == "dev"
Requires-Dist: pylint; extra == "dev"
Requires-Dist: pytest; extra == "dev"
Requires-Dist: pip-tools; extra == "dev"
Requires-Dist: pytest-asyncio; extra == "dev"
Requires-Dist: pandas; extra == "dev"
Requires-Dist: toml; extra == "dev"
Requires-Dist: yapf; extra == "dev"
Requires-Dist: twine; extra == "dev"
Requires-Dist: bumpver; extra == "dev"
Provides-Extra: ipython
Requires-Dist: ipykernel; extra == "ipython"
Requires-Dist: ipython; extra == "ipython"
Requires-Dist: pytest-notebook; extra == "ipython"
